flowingo-0.0.2.data/data/flowingo/ui/build/2.4510ecf8.js
flowingo-0.0.2.data/data/flowingo/ui/build/index.a6a80465.js
flowingo-0.0.2.data/data/flowingo/ui/build/index.html
flowingo-0.0.2.data/data/flowingo/ui/build/runtime.82af4b31.js
flowingo-0.0.2.data/platlib/flowingo/__init__.py
flowingo-0.0.2.data/platlib/flowingo/__main__.py
flowingo-0.0.2.data/platlib/flowingo/configuration.py
flowingo-0.0.2.data/platlib/flowingo/exceptions.py
flowingo-0.0.2.data/platlib/flowingo/api/__init__.py
flowingo-0.0.2.data/platlib/flowingo/api/auth/__init__.py
flowingo-0.0.2.data/platlib/flowingo/cli/__init__.py
flowingo-0.0.2.data/platlib/flowingo/cli/db_command.py
flowingo-0.0.2.data/platlib/flowingo/cli/manager_command.py
flowingo-0.0.2.data/platlib/flowingo/cli/pipeline_command.py
flowingo-0.0.2.data/platlib/flowingo/cli/webserver_command.py
flowingo-0.0.2.data/platlib/flowingo/manager/__init__.py
flowingo-0.0.2.data/platlib/flowingo/manager/app.py
flowingo-0.0.2.data/platlib/flowingo/manager/celeryconfig.py
flowingo-0.0.2.data/platlib/flowingo/manager/tasks/__init__.py
flowingo-0.0.2.data/platlib/flowingo/manager/tasks/pipelines.py
flowingo-0.0.2.data/platlib/flowingo/manager/tasks/runtime.py
flowingo-0.0.2.data/platlib/flowingo/models/__init__.py
flowingo-0.0.2.data/platlib/flowingo/models/auth.py
flowingo-0.0.2.data/platlib/flowingo/models/base.py
flowingo-0.0.2.data/platlib/flowingo/models/meta.py
flowingo-0.0.2.data/platlib/flowingo/models/pipelines.py
flowingo-0.0.2.data/platlib/flowingo/models/runs.py
flowingo-0.0.2.data/platlib/flowingo/models/tasks.py
flowingo-0.0.2.data/platlib/flowingo/pipelines/__init__.py
flowingo-0.0.2.data/platlib/flowingo/pipelines/reader.py
flowingo-0.0.2.data/platlib/flowingo/pipelines/utils.py
flowingo-0.0.2.data/platlib/flowingo/pipelines/validation.py
flowingo-0.0.2.data/platlib/flowingo/pipelines/writer.py
flowingo-0.0.2.data/platlib/flowingo/ui/build/index.html
flowingo-0.0.2.data/platlib/flowingo/ui/build/assets/2.4510ecf8.js
flowingo-0.0.2.dist-info/METADATA
flowingo-0.0.2.dist-info/WHEEL
flowingo-0.0.2.dist-info/entry_points.txt
flowingo-0.0.2.dist-info/top_level.txt
flowingo-0.0.2.dist-info/RECORD
